{"metric": "pe", "label": "P/E", "category": "Valuation", "format": "ratio", "isFlow": false, "currency": "USD", "lastReportedDate": "2026-03-31", "views": {"quarterly": {"current": 23.6693765985236, "qoq": -0.027188917813197544, "yoy": null, "cagr5y": null, "avg5y": 24.000142122689013, "peak": {"period": "2025-Q4", "value": 24.330907646854424}, "low": {"period": "2026-Q1", "value": 23.6693765985236}, "started": {"period": "2025-Q4", "value": 24.330907646854424}, "series": [{"period": "2025-Q1", "fiscalDate": "2025-03-31", "value": null}, {"period": "2025-Q2", "fiscalDate": "2025-06-30", "value": null}, {"period": "2025-Q3", "fiscalDate": "2025-09-30", "value": null}, {"period": "2025-Q4", "fiscalDate": "2025-12-31", "value": 24.330907646854424}, {"period": "2026-Q1", "fiscalDate": "2026-03-31", "value": 23.6693765985236}]}, "ttm": {"current": null, "qoq": null, "yoy": null, "cagr5y": null, "avg5y": null, "peak": null, "low": null, "started": null, "series": [{"period": "2025-Q1", "fiscalDate": "2025-03-31", "value": null}, {"period": "2025-Q2", "fiscalDate": "2025-06-30", "value": null}, {"period": "2025-Q3", "fiscalDate": "2025-09-30", "value": null}, {"period": "2025-Q4", "fiscalDate": "2025-12-31", "value": null}, {"period": "2026-Q1", "fiscalDate": "2026-03-31", "value": null}]}}}
