{"metric": "fcf", "label": "Free Cash Flow", "category": "Quality", "format": "currency", "isFlow": true, "currency": "USD", "lastReportedDate": "2026-03-31", "views": {"quarterly": {"current": 65964000.0, "qoq": -0.781865800708331, "yoy": -0.3607086438657531, "cagr5y": -0.061709464983318085, "avg5y": 163253650.0, "peak": {"period": "2022-Q4", "value": 762186000.0}, "low": {"period": "2020-Q3", "value": -174419000.0}, "started": {"period": "2016-Q2", "value": 122749000.0}, "series": [{"period": "2016-Q2", "fiscalDate": "2016-06-30", "value": 122749000.0}, {"period": "2016-Q3", "fiscalDate": "2016-09-30", "value": 106925000.0}, {"period": "2016-Q4", "fiscalDate": "2016-12-31", "value": 135253000.0}, {"period": "2017-Q1", "fiscalDate": "2017-03-31", "value": 79159000.0}, {"period": "2017-Q2", "fiscalDate": "2017-06-30", "value": 46747000.0}, {"period": "2017-Q3", "fiscalDate": "2017-09-30", "value": 60311000.0}, {"period": "2017-Q4", "fiscalDate": "2017-12-31", "value": 157662000.0}, {"period": "2018-Q1", "fiscalDate": "2018-03-31", "value": 188851000.0}, {"period": "2018-Q2", "fiscalDate": "2018-06-30", "value": 99050000.0}, {"period": "2018-Q3", "fiscalDate": "2018-09-30", "value": 205188000.0}, {"period": "2018-Q4", "fiscalDate": "2018-12-31", "value": 254807000.0}, {"period": "2019-Q1", "fiscalDate": "2019-03-31", "value": 248312000.0}, {"period": "2019-Q2", "fiscalDate": "2019-06-30", "value": 191440000.0}, {"period": "2019-Q3", "fiscalDate": "2019-09-30", "value": 157445000.0}, {"period": "2019-Q4", "fiscalDate": "2019-12-31", "value": 201932000.0}, {"period": "2020-Q1", "fiscalDate": "2020-03-31", "value": 50658000.0}, {"period": "2020-Q2", "fiscalDate": "2020-06-30", "value": 443364000.0}, {"period": "2020-Q3", "fiscalDate": "2020-09-30", "value": -174419000.0}, {"period": "2020-Q4", "fiscalDate": "2020-12-31", "value": 156455000.0}, {"period": "2021-Q1", "fiscalDate": "2021-03-31", "value": -62127000.0}, {"period": "2021-Q2", "fiscalDate": "2021-06-30", "value": 141869000.0}, {"period": "2021-Q3", "fiscalDate": "2021-09-30", "value": -87145000.0}, {"period": "2021-Q4", "fiscalDate": "2021-12-31", "value": 68161000.0}, {"period": "2022-Q1", "fiscalDate": "2022-03-31", "value": -23974000.0}, {"period": "2022-Q2", "fiscalDate": "2022-06-30", "value": 238522000.0}, {"period": "2022-Q3", "fiscalDate": "2022-09-30", "value": 611522000.0}, {"period": "2022-Q4", "fiscalDate": "2022-12-31", "value": 762186000.0}, {"period": "2023-Q1", "fiscalDate": "2023-03-31", "value": 243173000.0}, {"period": "2023-Q2", "fiscalDate": "2023-06-30", "value": 214524000.0}, {"period": "2023-Q3", "fiscalDate": "2023-09-30", "value": 201029000.0}, {"period": "2023-Q4", "fiscalDate": "2023-12-31", "value": 43231000.0}, {"period": "2024-Q1", "fiscalDate": "2024-03-31", "value": -41943000.0}, {"period": "2024-Q2", "fiscalDate": "2024-06-30", "value": 159804000.0}, {"period": "2024-Q3", "fiscalDate": "2024-09-30", "value": 103316000.0}, {"period": "2024-Q4", "fiscalDate": "2024-12-31", "value": 265254000.0}, {"period": "2025-Q1", "fiscalDate": "2025-03-31", "value": 103183000.0}, {"period": "2025-Q2", "fiscalDate": "2025-06-30", "value": 219836000.0}, {"period": "2025-Q3", "fiscalDate": "2025-09-30", "value": 269471000.0}, {"period": "2025-Q4", "fiscalDate": "2025-12-31", "value": 302401000.0}, {"period": "2026-Q1", "fiscalDate": "2026-03-31", "value": 65964000.0}]}, "ttm": {"current": 857672000.0, "qoq": -0.04159054007694796, "yoy": 0.3580278581347369, "cagr5y": 0.075874396166419, "avg5y": 657596459.4594594, "peak": {"period": "2023-Q1", "value": 1855403000.0}, "low": {"period": "2021-Q4", "value": 60758000.0}, "started": {"period": "2017-Q1", "value": 444086000.0}, "series": [{"period": "2016-Q2", "fiscalDate": "2016-06-30", "value": null}, {"period": "2016-Q3", "fiscalDate": "2016-09-30", "value": null}, {"period": "2016-Q4", "fiscalDate": "2016-12-31", "value": null}, {"period": "2017-Q1", "fiscalDate": "2017-03-31", "value": 444086000.0}, {"period": "2017-Q2", "fiscalDate": "2017-06-30", "value": 368084000.0}, {"period": "2017-Q3", "fiscalDate": "2017-09-30", "value": 321470000.0}, {"period": "2017-Q4", "fiscalDate": "2017-12-31", "value": 343879000.0}, {"period": "2018-Q1", "fiscalDate": "2018-03-31", "value": 453571000.0}, {"period": "2018-Q2", "fiscalDate": "2018-06-30", "value": 505874000.0}, {"period": "2018-Q3", "fiscalDate": "2018-09-30", "value": 650751000.0}, {"period": "2018-Q4", "fiscalDate": "2018-12-31", "value": 747896000.0}, {"period": "2019-Q1", "fiscalDate": "2019-03-31", "value": 807357000.0}, {"period": "2019-Q2", "fiscalDate": "2019-06-30", "value": 899747000.0}, {"period": "2019-Q3", "fiscalDate": "2019-09-30", "value": 852004000.0}, {"period": "2019-Q4", "fiscalDate": "2019-12-31", "value": 799129000.0}, {"period": "2020-Q1", "fiscalDate": "2020-03-31", "value": 601475000.0}, {"period": "2020-Q2", "fiscalDate": "2020-06-30", "value": 853399000.0}, {"period": "2020-Q3", "fiscalDate": "2020-09-30", "value": 521535000.0}, {"period": "2020-Q4", "fiscalDate": "2020-12-31", "value": 476058000.0}, {"period": "2021-Q1", "fiscalDate": "2021-03-31", "value": 363273000.0}, {"period": "2021-Q2", "fiscalDate": "2021-06-30", "value": 61778000.0}, {"period": "2021-Q3", "fiscalDate": "2021-09-30", "value": 149052000.0}, {"period": "2021-Q4", "fiscalDate": "2021-12-31", "value": 60758000.0}, {"period": "2022-Q1", "fiscalDate": "2022-03-31", "value": 98911000.0}, {"period": "2022-Q2", "fiscalDate": "2022-06-30", "value": 195564000.0}, {"period": "2022-Q3", "fiscalDate": "2022-09-30", "value": 894231000.0}, {"period": "2022-Q4", "fiscalDate": "2022-12-31", "value": 1588256000.0}, {"period": "2023-Q1", "fiscalDate": "2023-03-31", "value": 1855403000.0}, {"period": "2023-Q2", "fiscalDate": "2023-06-30", "value": 1831405000.0}, {"period": "2023-Q3", "fiscalDate": "2023-09-30", "value": 1420912000.0}, {"period": "2023-Q4", "fiscalDate": "2023-12-31", "value": 701957000.0}, {"period": "2024-Q1", "fiscalDate": "2024-03-31", "value": 416841000.0}, {"period": "2024-Q2", "fiscalDate": "2024-06-30", "value": 362121000.0}, {"period": "2024-Q3", "fiscalDate": "2024-09-30", "value": 264408000.0}, {"period": "2024-Q4", "fiscalDate": "2024-12-31", "value": 486431000.0}, {"period": "2025-Q1", "fiscalDate": "2025-03-31", "value": 631557000.0}, {"period": "2025-Q2", "fiscalDate": "2025-06-30", "value": 691589000.0}, {"period": "2025-Q3", "fiscalDate": "2025-09-30", "value": 857744000.0}, {"period": "2025-Q4", "fiscalDate": "2025-12-31", "value": 894891000.0}, {"period": "2026-Q1", "fiscalDate": "2026-03-31", "value": 857672000.0}]}}}
