{"metric": "revenue", "label": "Revenue", "category": "Growth", "format": "currency", "isFlow": true, "currency": "USD", "lastReportedDate": "2026-01-31", "views": {"quarterly": {"current": 2532000000.0, "qoq": 0.04111842105263164, "yoy": 0.1451831750339212, "cagr5y": 0.22585687815537536, "avg5y": 1277421800.0, "peak": {"period": "2026-Q1", "value": 2532000000.0}, "low": {"period": "2016-Q2", "value": 347677000.0}, "started": {"period": "2016-Q2", "value": 347677000.0}, "series": [{"period": "2016-Q2", "fiscalDate": "2016-04-30", "value": 347677000.0}, {"period": "2016-Q3", "fiscalDate": "2016-07-31", "value": 373657000.0}, {"period": "2016-Q4", "fiscalDate": "2016-10-31", "value": 413522000.0}, {"period": "2017-Q1", "fiscalDate": "2017-01-31", "value": 439584000.0}, {"period": "2017-Q2", "fiscalDate": "2017-04-30", "value": 479861000.0}, {"period": "2017-Q3", "fiscalDate": "2017-07-31", "value": 525320000.0}, {"period": "2017-Q4", "fiscalDate": "2017-10-31", "value": 555389000.0}, {"period": "2018-Q1", "fiscalDate": "2018-01-31", "value": 582480000.0}, {"period": "2018-Q2", "fiscalDate": "2018-04-30", "value": 618643000.0}, {"period": "2018-Q3", "fiscalDate": "2018-07-31", "value": 671720000.0}, {"period": "2018-Q4", "fiscalDate": "2018-10-31", "value": 743189000.0}, {"period": "2019-Q1", "fiscalDate": "2019-01-31", "value": 788628000.0}, {"period": "2019-Q2", "fiscalDate": "2019-04-30", "value": 825055000.0}, {"period": "2019-Q3", "fiscalDate": "2019-07-31", "value": 887752000.0}, {"period": "2019-Q4", "fiscalDate": "2019-10-31", "value": 938100000.0}, {"period": "2020-Q1", "fiscalDate": "2020-01-31", "value": 976299000.0}, {"period": "2020-Q2", "fiscalDate": "2020-04-30", "value": 1018385000.0}, {"period": "2020-Q3", "fiscalDate": "2020-07-31", "value": 1061967000.0}, {"period": "2020-Q4", "fiscalDate": "2020-10-31", "value": 1105960000.0}, {"period": "2021-Q1", "fiscalDate": "2021-01-31", "value": 1131684000.0}, {"period": "2021-Q2", "fiscalDate": "2021-04-30", "value": 1175033000.0}, {"period": "2021-Q3", "fiscalDate": "2021-07-31", "value": 1260361000.0}, {"period": "2021-Q4", "fiscalDate": "2021-10-31", "value": 1327263000.0}, {"period": "2022-Q1", "fiscalDate": "2022-01-31", "value": 1376343000.0}, {"period": "2022-Q2", "fiscalDate": "2022-04-30", "value": 1434657000.0}, {"period": "2022-Q3", "fiscalDate": "2022-07-31", "value": 1535798000.0}, {"period": "2022-Q4", "fiscalDate": "2022-10-31", "value": 1599103000.0}, {"period": "2023-Q1", "fiscalDate": "2023-01-31", "value": 1646442000.0}, {"period": "2023-Q2", "fiscalDate": "2023-04-30", "value": 1684000000.0}, {"period": "2023-Q3", "fiscalDate": "2023-07-31", "value": 1787000000.0}, {"period": "2023-Q4", "fiscalDate": "2023-10-31", "value": 1866000000.0}, {"period": "2024-Q1", "fiscalDate": "2024-01-31", "value": 1922000000.0}, {"period": "2024-Q2", "fiscalDate": "2024-04-30", "value": 1990000000.0}, {"period": "2024-Q3", "fiscalDate": "2024-07-31", "value": 2085000000.0}, {"period": "2024-Q4", "fiscalDate": "2024-10-31", "value": 2160000000.0}, {"period": "2025-Q1", "fiscalDate": "2025-01-31", "value": 2211000000.0}, {"period": "2025-Q2", "fiscalDate": "2025-04-30", "value": 2240000000.0}, {"period": "2025-Q3", "fiscalDate": "2025-07-31", "value": 2348000000.0}, {"period": "2025-Q4", "fiscalDate": "2025-10-31", "value": 2432000000.0}, {"period": "2026-Q1", "fiscalDate": "2026-01-31", "value": 2532000000.0}]}, "ttm": {"current": 9552000000.0, "qoq": 0.034774130646733736, "yoy": 0.1309495619228036, "cagr5y": 0.22178971955350457, "avg5y": 5064205972.972973, "peak": {"period": "2026-Q1", "value": 9552000000.0}, "low": {"period": "2017-Q1", "value": 1574440000.0}, "started": {"period": "2017-Q1", "value": 1574440000.0}, "series": [{"period": "2016-Q2", "fiscalDate": "2016-04-30", "value": null}, {"period": "2016-Q3", "fiscalDate": "2016-07-31", "value": null}, {"period": "2016-Q4", "fiscalDate": "2016-10-31", "value": null}, {"period": "2017-Q1", "fiscalDate": "2017-01-31", "value": 1574440000.0}, {"period": "2017-Q2", "fiscalDate": "2017-04-30", "value": 1706624000.0}, {"period": "2017-Q3", "fiscalDate": "2017-07-31", "value": 1858287000.0}, {"period": "2017-Q4", "fiscalDate": "2017-10-31", "value": 2000154000.0}, {"period": "2018-Q1", "fiscalDate": "2018-01-31", "value": 2143050000.0}, {"period": "2018-Q2", "fiscalDate": "2018-04-30", "value": 2281832000.0}, {"period": "2018-Q3", "fiscalDate": "2018-07-31", "value": 2428232000.0}, {"period": "2018-Q4", "fiscalDate": "2018-10-31", "value": 2616032000.0}, {"period": "2019-Q1", "fiscalDate": "2019-01-31", "value": 2822180000.0}, {"period": "2019-Q2", "fiscalDate": "2019-04-30", "value": 3028592000.0}, {"period": "2019-Q3", "fiscalDate": "2019-07-31", "value": 3244624000.0}, {"period": "2019-Q4", "fiscalDate": "2019-10-31", "value": 3439535000.0}, {"period": "2020-Q1", "fiscalDate": "2020-01-31", "value": 3627206000.0}, {"period": "2020-Q2", "fiscalDate": "2020-04-30", "value": 3820536000.0}, {"period": "2020-Q3", "fiscalDate": "2020-07-31", "value": 3994751000.0}, {"period": "2020-Q4", "fiscalDate": "2020-10-31", "value": 4162611000.0}, {"period": "2021-Q1", "fiscalDate": "2021-01-31", "value": 4317996000.0}, {"period": "2021-Q2", "fiscalDate": "2021-04-30", "value": 4474644000.0}, {"period": "2021-Q3", "fiscalDate": "2021-07-31", "value": 4673038000.0}, {"period": "2021-Q4", "fiscalDate": "2021-10-31", "value": 4894341000.0}, {"period": "2022-Q1", "fiscalDate": "2022-01-31", "value": 5139000000.0}, {"period": "2022-Q2", "fiscalDate": "2022-04-30", "value": 5398624000.0}, {"period": "2022-Q3", "fiscalDate": "2022-07-31", "value": 5674061000.0}, {"period": "2022-Q4", "fiscalDate": "2022-10-31", "value": 5945901000.0}, {"period": "2023-Q1", "fiscalDate": "2023-01-31", "value": 6216000000.0}, {"period": "2023-Q2", "fiscalDate": "2023-04-30", "value": 6465343000.0}, {"period": "2023-Q3", "fiscalDate": "2023-07-31", "value": 6716545000.0}, {"period": "2023-Q4", "fiscalDate": "2023-10-31", "value": 6983442000.0}, {"period": "2024-Q1", "fiscalDate": "2024-01-31", "value": 7259000000.0}, {"period": "2024-Q2", "fiscalDate": "2024-04-30", "value": 7565000000.0}, {"period": "2024-Q3", "fiscalDate": "2024-07-31", "value": 7863000000.0}, {"period": "2024-Q4", "fiscalDate": "2024-10-31", "value": 8157000000.0}, {"period": "2025-Q1", "fiscalDate": "2025-01-31", "value": 8446000000.0}, {"period": "2025-Q2", "fiscalDate": "2025-04-30", "value": 8696000000.0}, {"period": "2025-Q3", "fiscalDate": "2025-07-31", "value": 8959000000.0}, {"period": "2025-Q4", "fiscalDate": "2025-10-31", "value": 9231000000.0}, {"period": "2026-Q1", "fiscalDate": "2026-01-31", "value": 9552000000.0}]}}}
