{"metric": "roic", "label": "ROIC", "category": "Returns", "format": "percent", "isFlow": false, "currency": "USD", "lastReportedDate": "2026-01-31", "views": {"quarterly": {"current": 0.07576229244613361, "qoq": 0.5349276993787828, "yoy": 1.0340066544865252, "cagr5y": -0.2088824332890179, "avg5y": 0.06851580163273652, "peak": {"period": "2021-Q4", "value": 0.17203210716573242}, "low": {"period": "2025-Q1", "value": 0.03724780952855802}, "started": {"period": "2021-Q4", "value": 0.17203210716573242}, "series": [{"period": "2018-Q2", "fiscalDate": "2018-04-30", "value": null}, {"period": "2018-Q3", "fiscalDate": "2018-07-31", "value": null}, {"period": "2018-Q4", "fiscalDate": "2018-10-31", "value": null}, {"period": "2018-Q4", "fiscalDate": "2018-11-01", "value": null}, {"period": "2018-Q4", "fiscalDate": "2018-11-03", "value": null}, {"period": "2019-Q1", "fiscalDate": "2019-01-31", "value": null}, {"period": "2019-Q2", "fiscalDate": "2019-04-30", "value": null}, {"period": "2019-Q2", "fiscalDate": "2019-05-04", "value": null}, {"period": "2019-Q3", "fiscalDate": "2019-07-31", "value": null}, {"period": "2019-Q3", "fiscalDate": "2019-08-03", "value": null}, {"period": "2019-Q4", "fiscalDate": "2019-10-31", "value": null}, {"period": "2019-Q4", "fiscalDate": "2019-11-01", "value": null}, {"period": "2019-Q4", "fiscalDate": "2019-11-02", "value": null}, {"period": "2019-Q4", "fiscalDate": "2019-11-03", "value": null}, {"period": "2020-Q1", "fiscalDate": "2020-01-31", "value": null}, {"period": "2020-Q1", "fiscalDate": "2020-02-01", "value": null}, {"period": "2020-Q2", "fiscalDate": "2020-05-02", "value": null}, {"period": "2020-Q3", "fiscalDate": "2020-08-01", "value": null}, {"period": "2020-Q4", "fiscalDate": "2020-10-31", "value": null}, {"period": "2021-Q1", "fiscalDate": "2021-01-30", "value": null}, {"period": "2021-Q2", "fiscalDate": "2021-05-01", "value": null}, {"period": "2021-Q3", "fiscalDate": "2021-07-31", "value": null}, {"period": "2021-Q4", "fiscalDate": "2021-10-30", "value": 0.17203210716573242}, {"period": "2022-Q1", "fiscalDate": "2022-01-29", "value": null}, {"period": "2022-Q2", "fiscalDate": "2022-04-30", "value": null}, {"period": "2022-Q3", "fiscalDate": "2022-07-30", "value": null}, {"period": "2022-Q4", "fiscalDate": "2022-10-29", "value": 0.06332427938354473}, {"period": "2023-Q1", "fiscalDate": "2023-01-28", "value": 0.05881765984508476}, {"period": "2023-Q2", "fiscalDate": "2023-04-29", "value": 0.07026893937319878}, {"period": "2023-Q3", "fiscalDate": "2023-07-29", "value": 0.08045505390625811}, {"period": "2023-Q4", "fiscalDate": "2023-10-28", "value": 0.08353981146645711}, {"period": "2024-Q1", "fiscalDate": "2024-01-27", "value": 0.08807264888661799}, {"period": "2024-Q2", "fiscalDate": "2024-04-27", "value": 0.05935903527324254}, {"period": "2024-Q3", "fiscalDate": "2024-07-27", "value": 0.04427185290180951}, {"period": "2024-Q4", "fiscalDate": "2024-11-02", "value": 0.038551252376368084}, {"period": "2025-Q1", "fiscalDate": "2025-02-01", "value": 0.03724780952855802}, {"period": "2025-Q2", "fiscalDate": "2025-05-03", "value": 0.04696089031836594}, {"period": "2025-Q3", "fiscalDate": "2025-08-02", "value": 0.05971452443863819}, {"period": "2025-Q4", "fiscalDate": "2025-11-01", "value": 0.04935886718103803}, {"period": "2026-Q1", "fiscalDate": "2026-01-31", "value": 0.07576229244613361}]}, "ttm": {"current": 0.057949143596043945, "qoq": 0.1992656568714284, "yoy": 0.29184996306835065, "cagr5y": -0.06316506256514298, "avg5y": 0.06043689627154873, "peak": {"period": "2024-Q1", "value": 0.080584113408133}, "low": {"period": "2025-Q2", "value": 0.041757951281275386}, "started": {"period": "2023-Q3", "value": 0.0682164831270216}, "series": [{"period": "2018-Q2", "fiscalDate": "2018-04-30", "value": null}, {"period": "2018-Q3", "fiscalDate": "2018-07-31", "value": null}, {"period": "2018-Q4", "fiscalDate": "2018-10-31", "value": null}, {"period": "2018-Q4", "fiscalDate": "2018-11-01", "value": null}, {"period": "2018-Q4", "fiscalDate": "2018-11-03", "value": null}, {"period": "2019-Q1", "fiscalDate": "2019-01-31", "value": null}, {"period": "2019-Q2", "fiscalDate": "2019-04-30", "value": null}, {"period": "2019-Q2", "fiscalDate": "2019-05-04", "value": null}, {"period": "2019-Q3", "fiscalDate": "2019-07-31", "value": null}, {"period": "2019-Q3", "fiscalDate": "2019-08-03", "value": null}, {"period": "2019-Q4", "fiscalDate": "2019-10-31", "value": null}, {"period": "2019-Q4", "fiscalDate": "2019-11-01", "value": null}, {"period": "2019-Q4", "fiscalDate": "2019-11-02", "value": null}, {"period": "2019-Q4", "fiscalDate": "2019-11-03", "value": null}, {"period": "2020-Q1", "fiscalDate": "2020-01-31", "value": null}, {"period": "2020-Q1", "fiscalDate": "2020-02-01", "value": null}, {"period": "2020-Q2", "fiscalDate": "2020-05-02", "value": null}, {"period": "2020-Q3", "fiscalDate": "2020-08-01", "value": null}, {"period": "2020-Q4", "fiscalDate": "2020-10-31", "value": null}, {"period": "2021-Q1", "fiscalDate": "2021-01-30", "value": null}, {"period": "2021-Q2", "fiscalDate": "2021-05-01", "value": null}, {"period": "2021-Q3", "fiscalDate": "2021-07-31", "value": null}, {"period": "2021-Q4", "fiscalDate": "2021-10-30", "value": null}, {"period": "2022-Q1", "fiscalDate": "2022-01-29", "value": null}, {"period": "2022-Q2", "fiscalDate": "2022-04-30", "value": null}, {"period": "2022-Q3", "fiscalDate": "2022-07-30", "value": null}, {"period": "2022-Q4", "fiscalDate": "2022-10-29", "value": null}, {"period": "2023-Q1", "fiscalDate": "2023-01-28", "value": null}, {"period": "2023-Q2", "fiscalDate": "2023-04-29", "value": null}, {"period": "2023-Q3", "fiscalDate": "2023-07-29", "value": 0.0682164831270216}, {"period": "2023-Q4", "fiscalDate": "2023-10-28", "value": 0.07327036614774969}, {"period": "2024-Q1", "fiscalDate": "2024-01-27", "value": 0.080584113408133}, {"period": "2024-Q2", "fiscalDate": "2024-04-27", "value": 0.07785663738314394}, {"period": "2024-Q3", "fiscalDate": "2024-07-27", "value": 0.06881083713203179}, {"period": "2024-Q4", "fiscalDate": "2024-11-02", "value": 0.05756369735950953}, {"period": "2025-Q1", "fiscalDate": "2025-02-01", "value": 0.044857487519994535}, {"period": "2025-Q2", "fiscalDate": "2025-05-03", "value": 0.041757951281275386}, {"period": "2025-Q3", "fiscalDate": "2025-08-02", "value": 0.04561861916548256}, {"period": "2025-Q4", "fiscalDate": "2025-11-01", "value": 0.04832052286665005}, {"period": "2026-Q1", "fiscalDate": "2026-01-31", "value": 0.057949143596043945}]}}}
