{"metric": "roe", "label": "ROE", "category": "Returns", "format": "percent", "isFlow": false, "currency": "USD", "lastReportedDate": "2026-03-31", "views": {"quarterly": {"current": 0.29984785916105194, "qoq": -0.022835922928787, "yoy": -0.06866087820683564, "cagr5y": 0.01440167404851933, "avg5y": 0.3323430394983746, "peak": {"period": "2020-Q1", "value": 0.4982955513891256}, "low": {"period": "2019-Q1", "value": 0.19689484827099507}, "started": {"period": "2017-Q4", "value": 0.26935576371630665}, "series": [{"period": "2016-Q3", "fiscalDate": "2016-10-01", "value": null}, {"period": "2016-Q4", "fiscalDate": "2016-12-31", "value": null}, {"period": "2017-Q1", "fiscalDate": "2017-04-01", "value": null}, {"period": "2017-Q2", "fiscalDate": "2017-07-01", "value": null}, {"period": "2017-Q3", "fiscalDate": "2017-09-30", "value": null}, {"period": "2017-Q4", "fiscalDate": "2017-12-30", "value": 0.26935576371630665}, {"period": "2017-Q4", "fiscalDate": "2017-12-31", "value": null}, {"period": "2018-Q1", "fiscalDate": "2018-03-31", "value": null}, {"period": "2018-Q2", "fiscalDate": "2018-06-30", "value": null}, {"period": "2018-Q3", "fiscalDate": "2018-09-29", "value": null}, {"period": "2018-Q4", "fiscalDate": "2018-12-29", "value": 0.4893728405402576}, {"period": "2019-Q1", "fiscalDate": "2019-03-30", "value": 0.19689484827099507}, {"period": "2019-Q2", "fiscalDate": "2019-06-29", "value": 0.2288}, {"period": "2019-Q3", "fiscalDate": "2019-09-28", "value": 0.22526952903347836}, {"period": "2019-Q4", "fiscalDate": "2019-12-28", "value": 0.2521594684385382}, {"period": "2020-Q1", "fiscalDate": "2020-03-28", "value": 0.4982955513891256}, {"period": "2020-Q2", "fiscalDate": "2020-06-27", "value": 0.4291951561084109}, {"period": "2020-Q3", "fiscalDate": "2020-09-26", "value": 0.3947999400569459}, {"period": "2020-Q4", "fiscalDate": "2021-01-02", "value": 0.3743686443531551}, {"period": "2021-Q1", "fiscalDate": "2021-04-03", "value": 0.3990138441115115}, {"period": "2021-Q2", "fiscalDate": "2021-07-03", "value": 0.4316154026766847}, {"period": "2021-Q3", "fiscalDate": "2021-10-02", "value": 0.4162405513561583}, {"period": "2021-Q4", "fiscalDate": "2022-01-01", "value": 0.3845874038661401}, {"period": "2022-Q1", "fiscalDate": "2022-04-02", "value": 0.3771280724450194}, {"period": "2022-Q2", "fiscalDate": "2022-07-02", "value": 0.3921214311528731}, {"period": "2022-Q3", "fiscalDate": "2022-10-01", "value": 0.40696457928560753}, {"period": "2022-Q4", "fiscalDate": "2022-12-31", "value": 0.37255191418167505}, {"period": "2023-Q1", "fiscalDate": "2023-04-01", "value": 0.3329090998090949}, {"period": "2023-Q2", "fiscalDate": "2023-07-01", "value": 0.28086542278682014}, {"period": "2023-Q3", "fiscalDate": "2023-09-30", "value": 0.2339600697809653}, {"period": "2023-Q4", "fiscalDate": "2023-12-30", "value": 0.2363832886883782}, {"period": "2024-Q1", "fiscalDate": "2024-03-30", "value": 0.2514519056261343}, {"period": "2024-Q2", "fiscalDate": "2024-06-29", "value": 0.27572034454112193}, {"period": "2024-Q3", "fiscalDate": "2024-09-28", "value": 0.28154893688123983}, {"period": "2024-Q4", "fiscalDate": "2024-12-28", "value": 0.30484798685291703}, {"period": "2025-Q1", "fiscalDate": "2025-03-29", "value": 0.3219534669431007}, {"period": "2025-Q2", "fiscalDate": "2025-06-28", "value": 0.3229469476744186}, {"period": "2025-Q3", "fiscalDate": "2025-09-27", "value": 0.31460877431026685}, {"period": "2025-Q4", "fiscalDate": "2025-12-31", "value": 0.3068551804112216}, {"period": "2026-Q1", "fiscalDate": "2026-03-31", "value": 0.29984785916105194}]}, "ttm": {"current": 0.3110646903892398, "qoq": -0.017455961583621282, "yoy": 0.050831444903060685, "cagr5y": 0.013508262656783065, "avg5y": 0.33531984177920926, "peak": {"period": "2020-Q4", "value": 0.4241648229769094}, "low": {"period": "2019-Q4", "value": 0.2257809614357529}, "started": {"period": "2019-Q3", "value": 0.28508430446118277}, "series": [{"period": "2016-Q3", "fiscalDate": "2016-10-01", "value": null}, {"period": "2016-Q4", "fiscalDate": "2016-12-31", "value": null}, {"period": "2017-Q1", "fiscalDate": "2017-04-01", "value": null}, {"period": "2017-Q2", "fiscalDate": "2017-07-01", "value": null}, {"period": "2017-Q3", "fiscalDate": "2017-09-30", "value": null}, {"period": "2017-Q4", "fiscalDate": "2017-12-30", "value": null}, {"period": "2017-Q4", "fiscalDate": "2017-12-31", "value": null}, {"period": "2018-Q1", "fiscalDate": "2018-03-31", "value": null}, {"period": "2018-Q2", "fiscalDate": "2018-06-30", "value": null}, {"period": "2018-Q3", "fiscalDate": "2018-09-29", "value": null}, {"period": "2018-Q4", "fiscalDate": "2018-12-29", "value": null}, {"period": "2019-Q1", "fiscalDate": "2019-03-30", "value": null}, {"period": "2019-Q2", "fiscalDate": "2019-06-29", "value": null}, {"period": "2019-Q3", "fiscalDate": "2019-09-28", "value": 0.28508430446118277}, {"period": "2019-Q4", "fiscalDate": "2019-12-28", "value": 0.2257809614357529}, {"period": "2020-Q1", "fiscalDate": "2020-03-28", "value": 0.30113113721528556}, {"period": "2020-Q2", "fiscalDate": "2020-06-27", "value": 0.35122992624238825}, {"period": "2020-Q3", "fiscalDate": "2020-09-26", "value": 0.39361252899825516}, {"period": "2020-Q4", "fiscalDate": "2021-01-02", "value": 0.4241648229769094}, {"period": "2021-Q1", "fiscalDate": "2021-04-03", "value": 0.39934439615750583}, {"period": "2021-Q2", "fiscalDate": "2021-07-03", "value": 0.3999494577995743}, {"period": "2021-Q3", "fiscalDate": "2021-10-02", "value": 0.40530961062437737}, {"period": "2021-Q4", "fiscalDate": "2022-01-01", "value": 0.4078643005026236}, {"period": "2022-Q1", "fiscalDate": "2022-04-02", "value": 0.40239285758600063}, {"period": "2022-Q2", "fiscalDate": "2022-07-02", "value": 0.3925193647050477}, {"period": "2022-Q3", "fiscalDate": "2022-10-01", "value": 0.39020037168741006}, {"period": "2022-Q4", "fiscalDate": "2022-12-31", "value": 0.38719149926629376}, {"period": "2023-Q1", "fiscalDate": "2023-04-01", "value": 0.3761367561073127}, {"period": "2023-Q2", "fiscalDate": "2023-07-01", "value": 0.3483227540157994}, {"period": "2023-Q3", "fiscalDate": "2023-09-30", "value": 0.3050716266396388}, {"period": "2023-Q4", "fiscalDate": "2023-12-30", "value": 0.27102947026631463}, {"period": "2024-Q1", "fiscalDate": "2024-03-30", "value": 0.2506651717205745}, {"period": "2024-Q2", "fiscalDate": "2024-06-29", "value": 0.24937890215914993}, {"period": "2024-Q3", "fiscalDate": "2024-09-28", "value": 0.26127611893421854}, {"period": "2024-Q4", "fiscalDate": "2024-12-28", "value": 0.27839229347535327}, {"period": "2025-Q1", "fiscalDate": "2025-03-29", "value": 0.29601768380459487}, {"period": "2025-Q2", "fiscalDate": "2025-06-28", "value": 0.307824334587919}, {"period": "2025-Q3", "fiscalDate": "2025-09-27", "value": 0.3160892939451758}, {"period": "2025-Q4", "fiscalDate": "2025-12-31", "value": 0.3165910923347519}, {"period": "2026-Q1", "fiscalDate": "2026-03-31", "value": 0.3110646903892398}]}}}
