{"metric": "net_margin", "label": "Net Margin", "category": "Profitability", "format": "percent", "isFlow": false, "currency": "USD", "lastReportedDate": "2026-03-31", "views": {"quarterly": {"current": 0.23092320757005944, "qoq": 2.9743099408110227, "yoy": -0.0887563817479805, "cagr5y": -0.06829836259833966, "avg5y": 0.38011730228885926, "peak": {"period": "2024-Q3", "value": 2.267277023036031}, "low": {"period": "2025-Q4", "value": 0.0581039755351682}, "started": {"period": "2022-Q2", "value": 0.29580027658490426}, "series": [{"period": "2016-Q2", "fiscalDate": "2016-06-30", "value": null}, {"period": "2016-Q3", "fiscalDate": "2016-09-30", "value": null}, {"period": "2016-Q4", "fiscalDate": "2016-12-31", "value": null}, {"period": "2017-Q1", "fiscalDate": "2017-03-31", "value": null}, {"period": "2017-Q2", "fiscalDate": "2017-06-30", "value": null}, {"period": "2017-Q3", "fiscalDate": "2017-09-30", "value": null}, {"period": "2017-Q4", "fiscalDate": "2017-12-31", "value": null}, {"period": "2018-Q1", "fiscalDate": "2018-03-31", "value": null}, {"period": "2018-Q2", "fiscalDate": "2018-06-30", "value": null}, {"period": "2018-Q3", "fiscalDate": "2018-09-30", "value": null}, {"period": "2018-Q4", "fiscalDate": "2018-12-31", "value": null}, {"period": "2019-Q1", "fiscalDate": "2019-03-31", "value": null}, {"period": "2019-Q2", "fiscalDate": "2019-06-30", "value": null}, {"period": "2019-Q3", "fiscalDate": "2019-09-30", "value": null}, {"period": "2019-Q4", "fiscalDate": "2019-12-31", "value": null}, {"period": "2020-Q1", "fiscalDate": "2020-03-31", "value": null}, {"period": "2020-Q2", "fiscalDate": "2020-06-30", "value": null}, {"period": "2020-Q3", "fiscalDate": "2020-09-30", "value": null}, {"period": "2020-Q4", "fiscalDate": "2020-12-31", "value": null}, {"period": "2021-Q1", "fiscalDate": "2021-03-31", "value": null}, {"period": "2021-Q2", "fiscalDate": "2021-06-30", "value": null}, {"period": "2021-Q3", "fiscalDate": "2021-09-30", "value": null}, {"period": "2021-Q4", "fiscalDate": "2021-12-31", "value": null}, {"period": "2022-Q1", "fiscalDate": "2022-03-31", "value": null}, {"period": "2022-Q2", "fiscalDate": "2022-06-30", "value": 0.29580027658490426}, {"period": "2022-Q3", "fiscalDate": "2022-09-30", "value": 0.2604245640636846}, {"period": "2022-Q4", "fiscalDate": "2022-12-31", "value": null}, {"period": "2023-Q1", "fiscalDate": "2023-03-31", "value": 0.278801277327438}, {"period": "2023-Q2", "fiscalDate": "2023-06-30", "value": 0.24012823520212684}, {"period": "2023-Q3", "fiscalDate": "2023-09-30", "value": 0.3095544474827087}, {"period": "2023-Q4", "fiscalDate": "2023-12-31", "value": 0.29208780795957046}, {"period": "2024-Q1", "fiscalDate": "2024-03-31", "value": 0.26460636138055493}, {"period": "2024-Q2", "fiscalDate": "2024-06-30", "value": 0.2674894114210603}, {"period": "2024-Q3", "fiscalDate": "2024-09-30", "value": 2.267277023036031}, {"period": "2024-Q4", "fiscalDate": "2024-12-31", "value": 0.2782508298455766}, {"period": "2025-Q1", "fiscalDate": "2025-03-31", "value": 0.2534154456006229}, {"period": "2025-Q2", "fiscalDate": "2025-06-30", "value": 0.21746508288735153}, {"period": "2025-Q3", "fiscalDate": "2025-09-30", "value": 0.18743158843603117}, {"period": "2025-Q4", "fiscalDate": "2025-12-31", "value": 0.0581039755351682}, {"period": "2026-Q1", "fiscalDate": "2026-03-31", "value": 0.23092320757005944}]}, "ttm": {"current": 0.1734809636071526, "qoq": -0.03139549525382168, "yoy": -0.773703218013711, "cagr5y": -0.1918374357611472, "avg5y": 0.44898787156628445, "peak": {"period": "2024-Q3", "value": 0.7728651509493041}, "low": {"period": "2026-Q1", "value": 0.1734809636071526}, "started": {"period": "2023-Q4", "value": 0.28014294199296097}, "series": [{"period": "2016-Q2", "fiscalDate": "2016-06-30", "value": null}, {"period": "2016-Q3", "fiscalDate": "2016-09-30", "value": null}, {"period": "2016-Q4", "fiscalDate": "2016-12-31", "value": null}, {"period": "2017-Q1", "fiscalDate": "2017-03-31", "value": null}, {"period": "2017-Q2", "fiscalDate": "2017-06-30", "value": null}, {"period": "2017-Q3", "fiscalDate": "2017-09-30", "value": null}, {"period": "2017-Q4", "fiscalDate": "2017-12-31", "value": null}, {"period": "2018-Q1", "fiscalDate": "2018-03-31", "value": null}, {"period": "2018-Q2", "fiscalDate": "2018-06-30", "value": null}, {"period": "2018-Q3", "fiscalDate": "2018-09-30", "value": null}, {"period": "2018-Q4", "fiscalDate": "2018-12-31", "value": null}, {"period": "2019-Q1", "fiscalDate": "2019-03-31", "value": null}, {"period": "2019-Q2", "fiscalDate": "2019-06-30", "value": null}, {"period": "2019-Q3", "fiscalDate": "2019-09-30", "value": null}, {"period": "2019-Q4", "fiscalDate": "2019-12-31", "value": null}, {"period": "2020-Q1", "fiscalDate": "2020-03-31", "value": null}, {"period": "2020-Q2", "fiscalDate": "2020-06-30", "value": null}, {"period": "2020-Q3", "fiscalDate": "2020-09-30", "value": null}, {"period": "2020-Q4", "fiscalDate": "2020-12-31", "value": null}, {"period": "2021-Q1", "fiscalDate": "2021-03-31", "value": null}, {"period": "2021-Q2", "fiscalDate": "2021-06-30", "value": null}, {"period": "2021-Q3", "fiscalDate": "2021-09-30", "value": null}, {"period": "2021-Q4", "fiscalDate": "2021-12-31", "value": null}, {"period": "2022-Q1", "fiscalDate": "2022-03-31", "value": null}, {"period": "2022-Q2", "fiscalDate": "2022-06-30", "value": null}, {"period": "2022-Q3", "fiscalDate": "2022-09-30", "value": null}, {"period": "2022-Q4", "fiscalDate": "2022-12-31", "value": null}, {"period": "2023-Q1", "fiscalDate": "2023-03-31", "value": null}, {"period": "2023-Q2", "fiscalDate": "2023-06-30", "value": null}, {"period": "2023-Q3", "fiscalDate": "2023-09-30", "value": null}, {"period": "2023-Q4", "fiscalDate": "2023-12-31", "value": 0.28014294199296097}, {"period": "2024-Q1", "fiscalDate": "2024-03-31", "value": 0.2765942130062402}, {"period": "2024-Q2", "fiscalDate": "2024-06-30", "value": 0.2834345070609736}, {"period": "2024-Q3", "fiscalDate": "2024-09-30", "value": 0.7728651509493041}, {"period": "2024-Q4", "fiscalDate": "2024-12-31", "value": 0.7694059064208056}, {"period": "2025-Q1", "fiscalDate": "2025-03-31", "value": 0.7666081774758227}, {"period": "2025-Q2", "fiscalDate": "2025-06-30", "value": 0.7541020953423955}, {"period": "2025-Q3", "fiscalDate": "2025-09-30", "value": 0.23414073669239555}, {"period": "2025-Q4", "fiscalDate": "2025-12-31", "value": 0.17910402311479345}, {"period": "2026-Q1", "fiscalDate": "2026-03-31", "value": 0.1734809636071526}]}}}
