{"ticker": "WDC", "as_of": "2026-05-19", "fetched_at": "2026-05-19T23:36:43Z", "source": "openinsider", "summary": {"net_buy_sell_90d": -27477935.0, "insider_count_90d": 5, "cluster_signal": false, "latest_activity": "2026-05-11"}, "transactions": [{"filing_date": "2026-05-12", "trade_date": "2026-05-11", "insider_name": "Davis Brian Scott", "title": "Chief Sales, Mrktng Officer", "type": "S", "shares": -10000.0, "price": 500.69, "value": -5006895.0, "is_10b51": false}, {"filing_date": "2026-05-05", "trade_date": "2026-05-04", "insider_name": "Gubbi Vidyadhara K", "title": "Chief of Global Operations", "type": "S", "shares": -4674.0, "price": 443.19, "value": -2071447.0, "is_10b51": false}, {"filing_date": "2026-05-05", "trade_date": "2026-05-01", "insider_name": "Tan Irving", "title": "CEO", "type": "S", "shares": -20000.0, "price": 411.84, "value": -8236864.0, "is_10b51": false}, {"filing_date": "2026-04-22", "trade_date": "2026-04-21", "insider_name": "Tregillis Cynthia L", "title": "GC, Corp Sec", "type": "S", "shares": -363.0, "price": 377.09, "value": -136884.0, "is_10b51": false}, {"filing_date": "2026-03-10", "trade_date": "2026-03-06", "insider_name": "Gubbi Vidyadhara K", "title": "Chief of Global Operations", "type": "S", "shares": -8518.0, "price": 255.33, "value": -2174858.0, "is_10b51": false}, {"filing_date": "2026-03-05", "trade_date": "2026-03-04", "insider_name": "Tregillis Cynthia L", "title": "GC, Corp Sec", "type": "S", "shares": -9324.0, "price": 268.27, "value": -2501382.0, "is_10b51": false}, {"filing_date": "2026-03-05", "trade_date": "2026-03-04", "insider_name": "Gubbi Vidyadhara K", "title": "Chief of Global Operations", "type": "S", "shares": -10148.0, "price": 270.31, "value": -2743110.0, "is_10b51": false}, {"filing_date": "2026-03-03", "trade_date": "2026-03-02", "insider_name": "Cole Martin I", "title": "Dir", "type": "S", "shares": -6000.0, "price": 271.67, "value": -1630002.0, "is_10b51": false}, {"filing_date": "2026-02-27", "trade_date": "2026-02-26", "insider_name": "Tregillis Cynthia L", "title": "GC, Corp Sec", "type": "S", "shares": -214.0, "price": 286.11, "value": -61228.0, "is_10b51": false}, {"filing_date": "2026-02-24", "trade_date": "2026-02-23", "insider_name": "Tregillis Cynthia L", "title": "GC, Corp Sec", "type": "S", "shares": -438.0, "price": 282.33, "value": -123662.0, "is_10b51": false}, {"filing_date": "2026-02-19", "trade_date": "2026-02-17", "insider_name": "Davis Brian Scott", "title": "Chief Sales, Mrktng Officer", "type": "S", "shares": -10000.0, "price": 279.16, "value": -2791603.0, "is_10b51": false}]}
