{"metric": "fcf", "label": "Free Cash Flow", "category": "Quality", "format": "currency", "isFlow": true, "currency": "USD", "lastReportedDate": "2026-03-31", "views": {"quarterly": {"current": 208000000.0, "qoq": -0.8898305084745762, "yoy": -1.2861072902338377, "cagr5y": -0.1878158511687983, "avg5y": 1320825000.0, "peak": {"period": "2022-Q2", "value": 6454000000.0}, "low": {"period": "2020-Q1", "value": -1719000000.0}, "started": {"period": "2016-Q2", "value": 1581000000.0}, "series": [{"period": "2016-Q2", "fiscalDate": "2016-06-30", "value": 1581000000.0}, {"period": "2016-Q3", "fiscalDate": "2016-09-30", "value": -311000000.0}, {"period": "2016-Q4", "fiscalDate": "2016-12-31", "value": 270000000.0}, {"period": "2017-Q1", "fiscalDate": "2017-03-31", "value": 498000000.0}, {"period": "2017-Q2", "fiscalDate": "2017-06-30", "value": 198000000.0}, {"period": "2017-Q3", "fiscalDate": "2017-09-30", "value": 1243000000.0}, {"period": "2017-Q4", "fiscalDate": "2017-12-31", "value": 1941000000.0}, {"period": "2018-Q1", "fiscalDate": "2018-03-31", "value": -892000000.0}, {"period": "2018-Q2", "fiscalDate": "2018-06-30", "value": 1675000000.0}, {"period": "2018-Q3", "fiscalDate": "2018-09-30", "value": 333000000.0}, {"period": "2018-Q4", "fiscalDate": "2018-12-31", "value": 1863000000.0}, {"period": "2019-Q1", "fiscalDate": "2019-03-31", "value": 382000000.0}, {"period": "2019-Q2", "fiscalDate": "2019-06-30", "value": 1444000000.0}, {"period": "2019-Q3", "fiscalDate": "2019-09-30", "value": 1745000000.0}, {"period": "2019-Q4", "fiscalDate": "2019-12-31", "value": 1060000000.0}, {"period": "2020-Q1", "fiscalDate": "2020-03-31", "value": -1719000000.0}, {"period": "2020-Q2", "fiscalDate": "2020-06-30", "value": -207000000.0}, {"period": "2020-Q3", "fiscalDate": "2020-09-30", "value": 687000000.0}, {"period": "2020-Q4", "fiscalDate": "2020-12-31", "value": 871000000.0}, {"period": "2021-Q1", "fiscalDate": "2021-03-31", "value": 150000000.0}, {"period": "2021-Q2", "fiscalDate": "2021-06-30", "value": 1078000000.0}, {"period": "2021-Q3", "fiscalDate": "2021-09-30", "value": -1525000000.0}, {"period": "2021-Q4", "fiscalDate": "2021-12-31", "value": 3193000000.0}, {"period": "2022-Q1", "fiscalDate": "2022-03-31", "value": 2018000000.0}, {"period": "2022-Q2", "fiscalDate": "2022-06-30", "value": 6454000000.0}, {"period": "2022-Q3", "fiscalDate": "2022-09-30", "value": 1813000000.0}, {"period": "2022-Q4", "fiscalDate": "2022-12-31", "value": 3656000000.0}, {"period": "2023-Q1", "fiscalDate": "2023-03-31", "value": 3600000000.0}, {"period": "2023-Q2", "fiscalDate": "2023-06-30", "value": 3503000000.0}, {"period": "2023-Q3", "fiscalDate": "2023-09-30", "value": 4533000000.0}, {"period": "2023-Q4", "fiscalDate": "2023-12-31", "value": 591000000.0}, {"period": "2024-Q1", "fiscalDate": "2024-03-31", "value": 947000000.0}, {"period": "2024-Q2", "fiscalDate": "2024-06-30", "value": 2755000000.0}, {"period": "2024-Q3", "fiscalDate": "2024-09-30", "value": 1033000000.0}, {"period": "2024-Q4", "fiscalDate": "2024-12-31", "value": 1397000000.0}, {"period": "2025-Q1", "fiscalDate": "2025-03-31", "value": -727000000.0}, {"period": "2025-Q2", "fiscalDate": "2025-06-30", "value": 1944000000.0}, {"period": "2025-Q3", "fiscalDate": "2025-09-30", "value": 1662000000.0}, {"period": "2025-Q4", "fiscalDate": "2025-12-31", "value": 1888000000.0}, {"period": "2026-Q1", "fiscalDate": "2026-03-31", "value": 208000000.0}]}, "ttm": {"current": 5702000000.0, "qoq": 0.19614013006083497, "yoy": 0.2790489008524002, "cagr5y": 0.121106843725171, "avg5y": 5429162162.162162, "peak": {"period": "2023-Q1", "value": 15523000000.0}, "low": {"period": "2020-Q4", "value": -368000000.0}, "started": {"period": "2017-Q1", "value": 2038000000.0}, "series": [{"period": "2016-Q2", "fiscalDate": "2016-06-30", "value": null}, {"period": "2016-Q3", "fiscalDate": "2016-09-30", "value": null}, {"period": "2016-Q4", "fiscalDate": "2016-12-31", "value": null}, {"period": "2017-Q1", "fiscalDate": "2017-03-31", "value": 2038000000.0}, {"period": "2017-Q2", "fiscalDate": "2017-06-30", "value": 655000000.0}, {"period": "2017-Q3", "fiscalDate": "2017-09-30", "value": 2209000000.0}, {"period": "2017-Q4", "fiscalDate": "2017-12-31", "value": 3880000000.0}, {"period": "2018-Q1", "fiscalDate": "2018-03-31", "value": 2490000000.0}, {"period": "2018-Q2", "fiscalDate": "2018-06-30", "value": 3967000000.0}, {"period": "2018-Q3", "fiscalDate": "2018-09-30", "value": 3057000000.0}, {"period": "2018-Q4", "fiscalDate": "2018-12-31", "value": 2979000000.0}, {"period": "2019-Q1", "fiscalDate": "2019-03-31", "value": 4253000000.0}, {"period": "2019-Q2", "fiscalDate": "2019-06-30", "value": 4022000000.0}, {"period": "2019-Q3", "fiscalDate": "2019-09-30", "value": 5434000000.0}, {"period": "2019-Q4", "fiscalDate": "2019-12-31", "value": 4631000000.0}, {"period": "2020-Q1", "fiscalDate": "2020-03-31", "value": 2530000000.0}, {"period": "2020-Q2", "fiscalDate": "2020-06-30", "value": 879000000.0}, {"period": "2020-Q3", "fiscalDate": "2020-09-30", "value": -179000000.0}, {"period": "2020-Q4", "fiscalDate": "2020-12-31", "value": -368000000.0}, {"period": "2021-Q1", "fiscalDate": "2021-03-31", "value": 1501000000.0}, {"period": "2021-Q2", "fiscalDate": "2021-06-30", "value": 2786000000.0}, {"period": "2021-Q3", "fiscalDate": "2021-09-30", "value": 574000000.0}, {"period": "2021-Q4", "fiscalDate": "2021-12-31", "value": 2896000000.0}, {"period": "2022-Q1", "fiscalDate": "2022-03-31", "value": 4764000000.0}, {"period": "2022-Q2", "fiscalDate": "2022-06-30", "value": 10140000000.0}, {"period": "2022-Q3", "fiscalDate": "2022-09-30", "value": 13478000000.0}, {"period": "2022-Q4", "fiscalDate": "2022-12-31", "value": 13941000000.0}, {"period": "2023-Q1", "fiscalDate": "2023-03-31", "value": 15523000000.0}, {"period": "2023-Q2", "fiscalDate": "2023-06-30", "value": 12572000000.0}, {"period": "2023-Q3", "fiscalDate": "2023-09-30", "value": 15292000000.0}, {"period": "2023-Q4", "fiscalDate": "2023-12-31", "value": 12227000000.0}, {"period": "2024-Q1", "fiscalDate": "2024-03-31", "value": 9574000000.0}, {"period": "2024-Q2", "fiscalDate": "2024-06-30", "value": 8826000000.0}, {"period": "2024-Q3", "fiscalDate": "2024-09-30", "value": 5326000000.0}, {"period": "2024-Q4", "fiscalDate": "2024-12-31", "value": 6132000000.0}, {"period": "2025-Q1", "fiscalDate": "2025-03-31", "value": 4458000000.0}, {"period": "2025-Q2", "fiscalDate": "2025-06-30", "value": 3647000000.0}, {"period": "2025-Q3", "fiscalDate": "2025-09-30", "value": 4276000000.0}, {"period": "2025-Q4", "fiscalDate": "2025-12-31", "value": 4767000000.0}, {"period": "2026-Q1", "fiscalDate": "2026-03-31", "value": 5702000000.0}]}}}
