{"metric": "eps", "label": "EPS", "category": "Growth", "format": "perShare", "isFlow": true, "currency": "USD", "lastReportedDate": "2026-03-28", "views": {"quarterly": {"current": 1.99, "qoq": 0.8090909090909089, "yoy": -4.109375, "cagr5y": 0.24228052051424598, "avg5y": 0.13450000000000004, "peak": {"period": "2017-Q4", "value": 3.21}, "low": {"period": "2024-Q2", "value": -3.749999999999999}, "started": {"period": "2016-Q2", "value": 0.24}, "series": [{"period": "2016-Q2", "fiscalDate": "2016-07-02", "value": 0.24}, {"period": "2016-Q3", "fiscalDate": "2016-10-01", "value": -0.06}, {"period": "2016-Q4", "fiscalDate": "2016-12-31", "value": 0.19}, {"period": "2017-Q1", "fiscalDate": "2017-04-01", "value": -0.92}, {"period": "2017-Q2", "fiscalDate": "2017-07-01", "value": -0.9}, {"period": "2017-Q3", "fiscalDate": "2017-09-30", "value": 0.11}, {"period": "2017-Q4", "fiscalDate": "2017-12-30", "value": 3.21}, {"period": "2018-Q1", "fiscalDate": "2018-03-31", "value": 0.04}, {"period": "2018-Q2", "fiscalDate": "2018-06-30", "value": 0.52}, {"period": "2018-Q3", "fiscalDate": "2018-09-29", "value": 0.73}, {"period": "2018-Q4", "fiscalDate": "2018-12-29", "value": 0.24}, {"period": "2019-Q1", "fiscalDate": "2019-03-30", "value": -0.98}, {"period": "2019-Q2", "fiscalDate": "2019-06-29", "value": -0.34}, {"period": "2019-Q3", "fiscalDate": "2019-09-28", "value": 0.62}, {"period": "2019-Q4", "fiscalDate": "2019-12-28", "value": 0.64}, {"period": "2020-Q1", "fiscalDate": "2020-03-28", "value": 0.58}, {"period": "2020-Q2", "fiscalDate": "2020-06-27", "value": -0.06}, {"period": "2020-Q3", "fiscalDate": "2020-09-26", "value": 0.89}, {"period": "2020-Q4", "fiscalDate": "2020-12-26", "value": 1.1}, {"period": "2021-Q1", "fiscalDate": "2021-04-03", "value": 2.97}, {"period": "2021-Q2", "fiscalDate": "2021-07-03", "value": 0.29}, {"period": "2021-Q3", "fiscalDate": "2021-10-02", "value": 1.12}, {"period": "2021-Q4", "fiscalDate": "2022-01-01", "value": 0.78}, {"period": "2022-Q1", "fiscalDate": "2022-04-02", "value": 0.37}, {"period": "2022-Q2", "fiscalDate": "2022-07-02", "value": 0.52}, {"period": "2022-Q3", "fiscalDate": "2022-10-01", "value": -0.01}, {"period": "2022-Q4", "fiscalDate": "2022-12-31", "value": -0.46}, {"period": "2023-Q1", "fiscalDate": "2023-04-01", "value": -0.57}, {"period": "2023-Q2", "fiscalDate": "2023-07-01", "value": -0.8899999999999999}, {"period": "2023-Q3", "fiscalDate": "2023-09-30", "value": -1.02}, {"period": "2023-Q4", "fiscalDate": "2023-12-30", "value": -1.47}, {"period": "2024-Q1", "fiscalDate": "2024-03-30", "value": -1.88}, {"period": "2024-Q2", "fiscalDate": "2024-06-29", "value": -3.749999999999999}, {"period": "2024-Q3", "fiscalDate": "2024-09-28", "value": -1.21}, {"period": "2024-Q4", "fiscalDate": "2024-12-28", "value": -0.88}, {"period": "2025-Q1", "fiscalDate": "2025-03-29", "value": -0.64}, {"period": "2025-Q2", "fiscalDate": "2025-06-28", "value": 3.11}, {"period": "2025-Q3", "fiscalDate": "2025-09-27", "value": 0.06}, {"period": "2025-Q4", "fiscalDate": "2025-12-27", "value": 1.1}, {"period": "2026-Q1", "fiscalDate": "2026-03-28", "value": 1.99}]}, "ttm": {"current": 6.26, "qoq": 0.724517906336088, "yoy": -1.9660493827160495, "cagr5y": null, "avg5y": 0.337837837837838, "peak": {"period": "2026-Q1", "value": 6.26}, "low": {"period": "2024-Q3", "value": -8.309999999999999}, "started": {"period": "2017-Q1", "value": -0.55}, "series": [{"period": "2016-Q2", "fiscalDate": "2016-07-02", "value": null}, {"period": "2016-Q3", "fiscalDate": "2016-10-01", "value": null}, {"period": "2016-Q4", "fiscalDate": "2016-12-31", "value": null}, {"period": "2017-Q1", "fiscalDate": "2017-04-01", "value": -0.55}, {"period": "2017-Q2", "fiscalDate": "2017-07-01", "value": -1.69}, {"period": "2017-Q3", "fiscalDate": "2017-09-30", "value": -1.52}, {"period": "2017-Q4", "fiscalDate": "2017-12-30", "value": 1.5}, {"period": "2018-Q1", "fiscalDate": "2018-03-31", "value": 2.46}, {"period": "2018-Q2", "fiscalDate": "2018-06-30", "value": 3.88}, {"period": "2018-Q3", "fiscalDate": "2018-09-29", "value": 4.5}, {"period": "2018-Q4", "fiscalDate": "2018-12-29", "value": 1.53}, {"period": "2019-Q1", "fiscalDate": "2019-03-30", "value": 0.51}, {"period": "2019-Q2", "fiscalDate": "2019-06-29", "value": -0.35000000000000003}, {"period": "2019-Q3", "fiscalDate": "2019-09-28", "value": -0.46}, {"period": "2019-Q4", "fiscalDate": "2019-12-28", "value": -0.06}, {"period": "2020-Q1", "fiscalDate": "2020-03-28", "value": 1.5}, {"period": "2020-Q2", "fiscalDate": "2020-06-27", "value": 1.78}, {"period": "2020-Q3", "fiscalDate": "2020-09-26", "value": 2.05}, {"period": "2020-Q4", "fiscalDate": "2020-12-26", "value": 2.5100000000000002}, {"period": "2021-Q1", "fiscalDate": "2021-04-03", "value": 4.9}, {"period": "2021-Q2", "fiscalDate": "2021-07-03", "value": 5.25}, {"period": "2021-Q3", "fiscalDate": "2021-10-02", "value": 5.48}, {"period": "2021-Q4", "fiscalDate": "2022-01-01", "value": 5.16}, {"period": "2022-Q1", "fiscalDate": "2022-04-02", "value": 2.56}, {"period": "2022-Q2", "fiscalDate": "2022-07-02", "value": 2.79}, {"period": "2022-Q3", "fiscalDate": "2022-10-01", "value": 1.6600000000000001}, {"period": "2022-Q4", "fiscalDate": "2022-12-31", "value": 0.42}, {"period": "2023-Q1", "fiscalDate": "2023-04-01", "value": -0.5199999999999999}, {"period": "2023-Q2", "fiscalDate": "2023-07-01", "value": -1.93}, {"period": "2023-Q3", "fiscalDate": "2023-09-30", "value": -2.94}, {"period": "2023-Q4", "fiscalDate": "2023-12-30", "value": -3.9499999999999997}, {"period": "2024-Q1", "fiscalDate": "2024-03-30", "value": -5.26}, {"period": "2024-Q2", "fiscalDate": "2024-06-29", "value": -8.12}, {"period": "2024-Q3", "fiscalDate": "2024-09-28", "value": -8.309999999999999}, {"period": "2024-Q4", "fiscalDate": "2024-12-28", "value": -7.719999999999999}, {"period": "2025-Q1", "fiscalDate": "2025-03-29", "value": -6.479999999999999}, {"period": "2025-Q2", "fiscalDate": "2025-06-28", "value": 0.3799999999999999}, {"period": "2025-Q3", "fiscalDate": "2025-09-27", "value": 1.65}, {"period": "2025-Q4", "fiscalDate": "2025-12-27", "value": 3.63}, {"period": "2026-Q1", "fiscalDate": "2026-03-28", "value": 6.26}]}}}
