{"axisType": "product", "axisLabel": "Product", "axis": "ProductOrServiceAxis", "periods": ["2021-Q2", "2021-Q3", "2022-Q1", "2022-Q2", "2022-Q3", "2023-Q1", "2023-Q2", "2023-Q3", "2024-Q1", "2024-Q2"], "segments": [{"name": "ElectricDistributionContractsMember", "label": "Electric Distribution Contracts", "history": [{"period": "2021-Q2", "value": 765000000.0}, {"period": "2021-Q3", "value": 1181000000.0}, {"period": "2022-Q1", "value": 720000000.0}, {"period": "2022-Q2", "value": 836000000.0}, {"period": "2022-Q3", "value": 1282000000.0}, {"period": "2023-Q1", "value": 730000000.0}, {"period": "2023-Q2", "value": 784000000.0}, {"period": "2023-Q3", "value": 1281000000.0}, {"period": "2024-Q1", "value": 781000000.0}, {"period": "2024-Q2", "value": 983000000.0}]}, {"name": "ElectricityandRelatedProductsMember", "label": "Electricityand Related Products", "history": [{"period": "2021-Q2", "value": 0.0}, {"period": "2021-Q3", "value": 0.0}, {"period": "2022-Q1", "value": 0.0}, {"period": "2022-Q2", "value": 0.0}, {"period": "2022-Q3", "value": 0.0}, {"period": "2023-Q1", "value": 0.0}, {"period": "2023-Q2", "value": 0.0}, {"period": "2023-Q3", "value": 0.0}, {"period": "2024-Q1", "value": 0.0}, {"period": "2024-Q2", "value": 0.0}]}, {"name": "GasDistributionContractsMember", "label": "Gas Distribution Contracts", "history": [{"period": "2021-Q2", "value": 256000000.0}, {"period": "2021-Q3", "value": 142000000.0}, {"period": "2022-Q1", "value": 1047000000.0}, {"period": "2022-Q2", "value": 317000000.0}, {"period": "2022-Q3", "value": 160000000.0}, {"period": "2023-Q1", "value": 959000000.0}, {"period": "2023-Q2", "value": 274000000.0}, {"period": "2023-Q3", "value": 147000000.0}, {"period": "2024-Q1", "value": 922000000.0}, {"period": "2024-Q2", "value": 301000000.0}]}, {"name": "NaturalGasReservesMember", "label": "Natural Gas Reserves", "history": [{"period": "2021-Q2", "value": 0.0}, {"period": "2021-Q3", "value": 0.0}, {"period": "2022-Q1", "value": 0.0}, {"period": "2022-Q2", "value": 0.0}, {"period": "2022-Q3", "value": 0.0}, {"period": "2023-Q1", "value": 0.0}, {"period": "2023-Q2", "value": 0.0}, {"period": "2023-Q3", "value": 0.0}, {"period": "2024-Q1", "value": 0.0}, {"period": "2024-Q2", "value": 0.0}]}, {"name": "OtherContractRevenuesMember", "label": "Other Contract Revenues", "history": [{"period": "2021-Q2", "value": 81000000.0}, {"period": "2021-Q3", "value": 80000000.0}, {"period": "2022-Q1", "value": 85000000.0}, {"period": "2022-Q2", "value": 94000000.0}, {"period": "2022-Q3", "value": 94000000.0}, {"period": "2023-Q1", "value": 78000000.0}, {"period": "2023-Q2", "value": 94000000.0}, {"period": "2023-Q3", "value": 90000000.0}, {"period": "2024-Q1", "value": 84000000.0}, {"period": "2024-Q2", "value": 92000000.0}]}, {"name": "TransmissionMember", "label": "Transmission", "history": [{"period": "2021-Q2", "value": 405000000.0}, {"period": "2021-Q3", "value": 409000000.0}, {"period": "2022-Q1", "value": 392000000.0}, {"period": "2022-Q2", "value": 396000000.0}, {"period": "2022-Q3", "value": 400000000.0}, {"period": "2023-Q1", "value": 425000000.0}, {"period": "2023-Q2", "value": 447000000.0}, {"period": "2023-Q3", "value": 422000000.0}, {"period": "2024-Q1", "value": 436000000.0}, {"period": "2024-Q2", "value": 436000000.0}]}], "generatedAt": "2026-05-14T19:14:04Z"}
