{"ticker": "ARE", "as_of": "2026-05-19", "fetched_at": "2026-05-19T23:34:16Z", "source": "openinsider", "summary": {"net_buy_sell_90d": 944047.0, "insider_count_90d": 4, "cluster_signal": false, "latest_activity": "2026-05-06"}, "transactions": [{"filing_date": "2026-05-07", "trade_date": "2026-05-06", "insider_name": "Marcus Joel S", "title": "Exec COB", "type": "P", "shares": 7500.0, "price": 46.34, "value": 347558.0, "is_10b51": false}, {"filing_date": "2026-05-06", "trade_date": "2026-05-05", "insider_name": "Marcus Joel S", "title": "Exec COB", "type": "P", "shares": 7500.0, "price": 42.72, "value": 320416.0, "is_10b51": false}, {"filing_date": "2026-05-05", "trade_date": "2026-05-04", "insider_name": "Marcus Joel S", "title": "Exec COB", "type": "P", "shares": 10000.0, "price": 41.02, "value": 410200.0, "is_10b51": false}, {"filing_date": "2026-05-04", "trade_date": "2026-04-30", "insider_name": "Thomas Gregory Calvin", "title": "EVP - CTO", "type": "P", "shares": 3500.0, "price": 41.0, "value": 143500.0, "is_10b51": false}, {"filing_date": "2026-04-21", "trade_date": "2026-04-17", "insider_name": "Kuhn Hallie E.", "title": "EVP - Cap Market, Co-Lead -LS", "type": "S", "shares": -536.0, "price": 48.2, "value": -25835.0, "is_10b51": false}, {"filing_date": "2026-03-03", "trade_date": "2026-02-27", "insider_name": "Gossett Bret E.", "title": "EVP - Co-RMD", "type": "S", "shares": -4702.0, "price": 53.55, "value": -251792.0, "is_10b51": false}]}
