{"metric": "roa", "label": "ROA", "category": "Returns", "format": "percent", "isFlow": false, "currency": "USD", "lastReportedDate": "2026-03-31", "views": {"quarterly": {"current": -0.001352044384353583, "qoq": -0.9625540980841739, "yoy": -0.3425958244131585, "cagr5y": null, "avg5y": 0.035414529332727734, "peak": {"period": "2022-Q4", "value": 0.14189336235038086}, "low": {"period": "2020-Q4", "value": -0.041619654744443194}, "started": {"period": "2018-Q4", "value": 0.020448864542892093}, "series": [{"period": "2016-Q4", "fiscalDate": "2017-01-01", "value": null}, {"period": "2017-Q1", "fiscalDate": "2017-03-31", "value": null}, {"period": "2017-Q2", "fiscalDate": "2017-06-30", "value": null}, {"period": "2017-Q3", "fiscalDate": "2017-09-01", "value": null}, {"period": "2017-Q3", "fiscalDate": "2017-09-30", "value": null}, {"period": "2017-Q4", "fiscalDate": "2017-12-31", "value": null}, {"period": "2017-Q4", "fiscalDate": "2018-01-01", "value": null}, {"period": "2018-Q1", "fiscalDate": "2018-03-31", "value": null}, {"period": "2018-Q2", "fiscalDate": "2018-06-30", "value": null}, {"period": "2018-Q3", "fiscalDate": "2018-09-30", "value": null}, {"period": "2018-Q4", "fiscalDate": "2018-12-31", "value": 0.020448864542892093}, {"period": "2019-Q1", "fiscalDate": "2019-03-31", "value": 0.017245830808546515}, {"period": "2019-Q2", "fiscalDate": "2019-06-30", "value": 0.013169967392685233}, {"period": "2019-Q3", "fiscalDate": "2019-09-30", "value": 0.01146622170880931}, {"period": "2019-Q4", "fiscalDate": "2019-12-31", "value": 0.007176206121390282}, {"period": "2020-Q1", "fiscalDate": "2020-03-31", "value": -0.009398855663582744}, {"period": "2020-Q2", "fiscalDate": "2020-06-30", "value": -0.038140607912752984}, {"period": "2020-Q3", "fiscalDate": "2020-09-30", "value": -0.04154364369775856}, {"period": "2020-Q4", "fiscalDate": "2020-12-31", "value": -0.041619654744443194}, {"period": "2021-Q1", "fiscalDate": "2021-03-31", "value": 0.06399046104928457}, {"period": "2021-Q2", "fiscalDate": "2021-06-30", "value": 0.13122014005541133}, {"period": "2021-Q3", "fiscalDate": "2021-09-30", "value": 0.14093230468325546}, {"period": "2021-Q4", "fiscalDate": "2021-12-31", "value": 0.14148817467783928}, {"period": "2022-Q1", "fiscalDate": "2022-03-31", "value": 0.03438856211310114}, {"period": "2022-Q2", "fiscalDate": "2022-06-30", "value": 0.04207920792079208}, {"period": "2022-Q3", "fiscalDate": "2022-09-30", "value": 0.04186035964534343}, {"period": "2022-Q4", "fiscalDate": "2022-12-31", "value": 0.14189336235038086}, {"period": "2023-Q1", "fiscalDate": "2023-03-31", "value": 0.13679382644146768}, {"period": "2023-Q2", "fiscalDate": "2023-06-30", "value": 0.11567026987278477}, {"period": "2023-Q3", "fiscalDate": "2023-09-30", "value": 0.11936217514629596}, {"period": "2023-Q4", "fiscalDate": "2023-12-31", "value": 0.010972193401120564}, {"period": "2024-Q1", "fiscalDate": "2024-03-31", "value": 0.00938568815123154}, {"period": "2024-Q2", "fiscalDate": "2024-06-30", "value": 0.018138046124805077}, {"period": "2024-Q3", "fiscalDate": "2024-09-30", "value": 0.021302154240410025}, {"period": "2024-Q4", "fiscalDate": "2024-12-31", "value": 0.01918877606725625}, {"period": "2025-Q1", "fiscalDate": "2025-03-31", "value": -0.002056641004974848}, {"period": "2025-Q2", "fiscalDate": "2025-06-30", "value": -0.005279137831997593}, {"period": "2025-Q3", "fiscalDate": "2025-09-30", "value": -0.020239722426663862}, {"period": "2025-Q4", "fiscalDate": "2025-12-31", "value": -0.03610660486674391}, {"period": "2026-Q1", "fiscalDate": "2026-03-31", "value": -0.001352044384353583}]}, "ttm": {"current": -0.015744377377439736, "qoq": -0.011064279488161355, "yoy": -2.1132209592172724, "cagr5y": null, "avg5y": 0.03923374409816747, "peak": {"period": "2023-Q3", "value": 0.1284299084527323}, "low": {"period": "2020-Q4", "value": -0.03267569050463437}, "started": {"period": "2019-Q3", "value": 0.015582721113233288}, "series": [{"period": "2016-Q4", "fiscalDate": "2017-01-01", "value": null}, {"period": "2017-Q1", "fiscalDate": "2017-03-31", "value": null}, {"period": "2017-Q2", "fiscalDate": "2017-06-30", "value": null}, {"period": "2017-Q3", "fiscalDate": "2017-09-01", "value": null}, {"period": "2017-Q3", "fiscalDate": "2017-09-30", "value": null}, {"period": "2017-Q4", "fiscalDate": "2017-12-31", "value": null}, {"period": "2017-Q4", "fiscalDate": "2018-01-01", "value": null}, {"period": "2018-Q1", "fiscalDate": "2018-03-31", "value": null}, {"period": "2018-Q2", "fiscalDate": "2018-06-30", "value": null}, {"period": "2018-Q3", "fiscalDate": "2018-09-30", "value": null}, {"period": "2018-Q4", "fiscalDate": "2018-12-31", "value": null}, {"period": "2019-Q1", "fiscalDate": "2019-03-31", "value": null}, {"period": "2019-Q2", "fiscalDate": "2019-06-30", "value": null}, {"period": "2019-Q3", "fiscalDate": "2019-09-30", "value": 0.015582721113233288}, {"period": "2019-Q4", "fiscalDate": "2019-12-31", "value": 0.012264556507857835}, {"period": "2020-Q1", "fiscalDate": "2020-03-31", "value": 0.00560338488982552}, {"period": "2020-Q2", "fiscalDate": "2020-06-30", "value": -0.007224258936534034}, {"period": "2020-Q3", "fiscalDate": "2020-09-30", "value": -0.020476725288176}, {"period": "2020-Q4", "fiscalDate": "2020-12-31", "value": -0.03267569050463437}, {"period": "2021-Q1", "fiscalDate": "2021-03-31", "value": -0.01432836132641754}, {"period": "2021-Q2", "fiscalDate": "2021-06-30", "value": 0.02801182566562354}, {"period": "2021-Q3", "fiscalDate": "2021-09-30", "value": 0.07363081276087705}, {"period": "2021-Q4", "fiscalDate": "2021-12-31", "value": 0.11940777011644765}, {"period": "2022-Q1", "fiscalDate": "2022-03-31", "value": 0.1120072953824018}, {"period": "2022-Q2", "fiscalDate": "2022-06-30", "value": 0.089722062348747}, {"period": "2022-Q3", "fiscalDate": "2022-09-30", "value": 0.06495407608926898}, {"period": "2022-Q4", "fiscalDate": "2022-12-31", "value": 0.06505537300740438}, {"period": "2023-Q1", "fiscalDate": "2023-03-31", "value": 0.090656689089496}, {"period": "2023-Q2", "fiscalDate": "2023-06-30", "value": 0.10905445457749419}, {"period": "2023-Q3", "fiscalDate": "2023-09-30", "value": 0.1284299084527323}, {"period": "2023-Q4", "fiscalDate": "2023-12-31", "value": 0.09569961621541724}, {"period": "2024-Q1", "fiscalDate": "2024-03-31", "value": 0.06384758164285821}, {"period": "2024-Q2", "fiscalDate": "2024-06-30", "value": 0.039464525705863285}, {"period": "2024-Q3", "fiscalDate": "2024-09-30", "value": 0.014949520479391801}, {"period": "2024-Q4", "fiscalDate": "2024-12-31", "value": 0.017003666145925724}, {"period": "2025-Q1", "fiscalDate": "2025-03-31", "value": 0.014143083856874126}, {"period": "2025-Q2", "fiscalDate": "2025-06-30", "value": 0.008288787867673458}, {"period": "2025-Q3", "fiscalDate": "2025-09-30", "value": -0.002096681299095013}, {"period": "2025-Q4", "fiscalDate": "2025-12-31", "value": -0.015920526532595056}, {"period": "2026-Q1", "fiscalDate": "2026-03-31", "value": -0.015744377377439736}]}}}
