{"metric": "pe", "label": "P/E", "category": "Valuation", "format": "ratio", "isFlow": false, "currency": "USD", "lastReportedDate": "2026-03-31", "views": {"quarterly": {"current": 12.910837139448839, "qoq": -0.13858034179714052, "yoy": -0.9530902690921879, "cagr5y": null, "avg5y": 20.766038623884402, "peak": {"period": "2024-Q4", "value": 431.6874980926516}, "low": {"period": "2017-Q1", "value": -252.20754371499115}, "started": {"period": "2017-Q1", "value": -252.20754371499115}, "series": [{"period": "2016-Q2", "fiscalDate": "2016-06-30", "value": null}, {"period": "2016-Q3", "fiscalDate": "2016-09-30", "value": null}, {"period": "2016-Q4", "fiscalDate": "2016-12-31", "value": null}, {"period": "2017-Q1", "fiscalDate": "2017-03-31", "value": -252.20754371499115}, {"period": "2017-Q2", "fiscalDate": "2017-06-30", "value": -163.5194852754667}, {"period": "2017-Q3", "fiscalDate": "2017-09-30", "value": -145.9249973297119}, {"period": "2017-Q4", "fiscalDate": "2017-12-31", "value": -60.711537874661964}, {"period": "2018-Q1", "fiscalDate": "2018-03-31", "value": -105.48101497601861}, {"period": "2018-Q2", "fiscalDate": "2018-06-30", "value": -139.58333333333337}, {"period": "2018-Q3", "fiscalDate": "2018-09-30", "value": -135.45098398246017}, {"period": "2018-Q4", "fiscalDate": "2018-12-31", "value": 122.28846183189978}, {"period": "2019-Q1", "fiscalDate": "2019-03-31", "value": 72.2773127195214}, {"period": "2019-Q2", "fiscalDate": "2019-06-30", "value": 59.412586772358495}, {"period": "2019-Q3", "fiscalDate": "2019-09-30", "value": 39.275134051287615}, {"period": "2019-Q4", "fiscalDate": "2019-12-31", "value": 41.9807690840501}, {"period": "2020-Q1", "fiscalDate": "2020-03-31", "value": -42.329481709210164}, {"period": "2020-Q2", "fiscalDate": "2020-06-30", "value": -116.82022609067766}, {"period": "2020-Q3", "fiscalDate": "2020-09-30", "value": -57.52563965626251}, {"period": "2020-Q4", "fiscalDate": "2020-12-31", "value": -62.575541983405465}, {"period": "2021-Q1", "fiscalDate": "2021-03-31", "value": 37.27981497388367}, {"period": "2021-Q2", "fiscalDate": "2021-06-30", "value": 54.98692630942351}, {"period": "2021-Q3", "fiscalDate": "2021-09-30", "value": 28.421487098883006}, {"period": "2021-Q4", "fiscalDate": "2021-12-31", "value": 17.069767796716025}, {"period": "2022-Q1", "fiscalDate": "2022-03-31", "value": 18.775413278710477}, {"period": "2022-Q2", "fiscalDate": "2022-06-30", "value": 17.750000285211012}, {"period": "2022-Q3", "fiscalDate": "2022-09-30", "value": 16.78589405280817}, {"period": "2022-Q4", "fiscalDate": "2022-12-31", "value": 52.496731826682506}, {"period": "2023-Q1", "fiscalDate": "2023-03-31", "value": 49.49999770073042}, {"period": "2023-Q2", "fiscalDate": "2023-06-30", "value": 37.957317073170735}, {"period": "2023-Q3", "fiscalDate": "2023-09-30", "value": 30.566137808340567}, {"period": "2023-Q4", "fiscalDate": "2023-12-31", "value": 23.516854275478405}, {"period": "2024-Q1", "fiscalDate": "2024-03-31", "value": 17.108108474685622}, {"period": "2024-Q2", "fiscalDate": "2024-06-30", "value": 159.52631297864417}, {"period": "2024-Q3", "fiscalDate": "2024-09-30", "value": 388.8235204360066}, {"period": "2024-Q4", "fiscalDate": "2024-12-31", "value": 431.6874980926516}, {"period": "2025-Q1", "fiscalDate": "2025-03-31", "value": 275.22726925936644}, {"period": "2025-Q2", "fiscalDate": "2025-06-30", "value": 15.655172063016344}, {"period": "2025-Q3", "fiscalDate": "2025-09-30", "value": 14.206029741807999}, {"period": "2025-Q4", "fiscalDate": "2025-12-31", "value": 14.987859885139061}, {"period": "2026-Q1", "fiscalDate": "2026-03-31", "value": 12.910837139448839}]}, "ttm": {"current": 14.43997470735306, "qoq": -0.8195433612410534, "yoy": -0.953985877723203, "cagr5y": null, "avg5y": 31.02975040022116, "peak": {"period": "2025-Q1", "value": 313.8161501916672}, "low": {"period": "2017-Q4", "value": -155.59089104870793}, "started": {"period": "2017-Q4", "value": -155.59089104870793}, "series": [{"period": "2016-Q2", "fiscalDate": "2016-06-30", "value": null}, {"period": "2016-Q3", "fiscalDate": "2016-09-30", "value": null}, {"period": "2016-Q4", "fiscalDate": "2016-12-31", "value": null}, {"period": "2017-Q1", "fiscalDate": "2017-03-31", "value": null}, {"period": "2017-Q2", "fiscalDate": "2017-06-30", "value": null}, {"period": "2017-Q3", "fiscalDate": "2017-09-30", "value": null}, {"period": "2017-Q4", "fiscalDate": "2017-12-31", "value": -155.59089104870793}, {"period": "2018-Q1", "fiscalDate": "2018-03-31", "value": -118.9092588639648}, {"period": "2018-Q2", "fiscalDate": "2018-06-30", "value": -112.92522087843146}, {"period": "2018-Q3", "fiscalDate": "2018-09-30", "value": -110.30671754161853}, {"period": "2018-Q4", "fiscalDate": "2018-12-31", "value": -64.5567176149781}, {"period": "2019-Q1", "fiscalDate": "2019-03-31", "value": -20.11713569109309}, {"period": "2019-Q2", "fiscalDate": "2019-06-30", "value": 29.631844335329877}, {"period": "2019-Q3", "fiscalDate": "2019-09-30", "value": 73.31337384376683}, {"period": "2019-Q4", "fiscalDate": "2019-12-31", "value": 53.23645065680441}, {"period": "2020-Q1", "fiscalDate": "2020-03-31", "value": 24.584752049621514}, {"period": "2020-Q2", "fiscalDate": "2020-06-30", "value": -19.47345116613753}, {"period": "2020-Q3", "fiscalDate": "2020-09-30", "value": -43.67364459302506}, {"period": "2020-Q4", "fiscalDate": "2020-12-31", "value": -69.81272235988895}, {"period": "2021-Q1", "fiscalDate": "2021-03-31", "value": -49.9103981891155}, {"period": "2021-Q2", "fiscalDate": "2021-06-30", "value": -6.9586100890902}, {"period": "2021-Q3", "fiscalDate": "2021-09-30", "value": 14.52817159969618}, {"period": "2021-Q4", "fiscalDate": "2021-12-31", "value": 34.43949904472655}, {"period": "2022-Q1", "fiscalDate": "2022-03-31", "value": 29.813398620933256}, {"period": "2022-Q2", "fiscalDate": "2022-06-30", "value": 20.50416711488013}, {"period": "2022-Q3", "fiscalDate": "2022-09-30", "value": 17.59526885336142}, {"period": "2022-Q4", "fiscalDate": "2022-12-31", "value": 26.452009860853043}, {"period": "2023-Q1", "fiscalDate": "2023-03-31", "value": 34.133155966358025}, {"period": "2023-Q2", "fiscalDate": "2023-06-30", "value": 39.18498516334796}, {"period": "2023-Q3", "fiscalDate": "2023-09-30", "value": 42.630046102231056}, {"period": "2023-Q4", "fiscalDate": "2023-12-31", "value": 35.38507671443003}, {"period": "2024-Q1", "fiscalDate": "2024-03-31", "value": 27.287104407918832}, {"period": "2024-Q2", "fiscalDate": "2024-06-30", "value": 57.67935338428719}, {"period": "2024-Q3", "fiscalDate": "2024-09-30", "value": 147.2436990412037}, {"period": "2024-Q4", "fiscalDate": "2024-12-31", "value": 249.286359995497}, {"period": "2025-Q1", "fiscalDate": "2025-03-31", "value": 313.8161501916672}, {"period": "2025-Q2", "fiscalDate": "2025-06-30", "value": 277.84836496276023}, {"period": "2025-Q3", "fiscalDate": "2025-09-30", "value": 184.1939922892106}, {"period": "2025-Q4", "fiscalDate": "2025-12-31", "value": 80.01908273733245}, {"period": "2026-Q1", "fiscalDate": "2026-03-31", "value": 14.43997470735306}]}}}
