{"axisType": "geographic", "axisLabel": "Geographic", "axis": "StatementGeographicalAxis", "periods": ["2021-Q2", "2021-Q3", "2022-Q1", "2022-Q2", "2022-Q3", "2023-Q1", "2023-Q2", "2023-Q3", "2024-Q1", "2024-Q2", "2024-Q3", "2025-Q1", "2025-Q2", "2025-Q3", "2026-Q1"], "segments": [{"name": "AmericasMember", "label": "Americas", "history": [{"period": "2021-Q2", "value": 337000000.0}, {"period": "2021-Q3", "value": 350100000.0}, {"period": "2022-Q1", "value": 382600000.0}, {"period": "2022-Q2", "value": 413600000.0}, {"period": "2022-Q3", "value": 467600000.0}, {"period": "2023-Q1", "value": 523500000.0}, {"period": "2023-Q2", "value": 537000000.0}, {"period": "2023-Q3", "value": 545600000.0}, {"period": "2024-Q1", "value": 557000000.0}, {"period": "2024-Q2", "value": 595300000.0}, {"period": "2024-Q3", "value": 624000000.0}, {"period": "2025-Q1", "value": 629800000.0}, {"period": "2025-Q2", "value": 658800000.0}, {"period": "2025-Q3", "value": 680500000.0}, {"period": "2026-Q1", "value": 739800000.0}]}, {"name": "AsiaPacificAndJapanMember", "label": "Asia Pacific And Japan", "history": [{"period": "2021-Q2", "value": 157900000.0}, {"period": "2021-Q3", "value": 193900000.0}, {"period": "2022-Q1", "value": 226200000.0}, {"period": "2022-Q2", "value": 224700000.0}, {"period": "2022-Q3", "value": 238000000.0}, {"period": "2023-Q1", "value": 260600000.0}, {"period": "2023-Q2", "value": 248900000.0}, {"period": "2023-Q3", "value": 276800000.0}, {"period": "2024-Q1", "value": 256900000.0}, {"period": "2024-Q2", "value": 273800000.0}, {"period": "2024-Q3", "value": null}, {"period": "2025-Q1", "value": null}, {"period": "2025-Q2", "value": null}, {"period": "2025-Q3", "value": null}, {"period": "2026-Q1", "value": null}]}, {"name": "AsiaPacificMember", "label": "Asia Pacific", "history": [{"period": "2021-Q2", "value": null}, {"period": "2021-Q3", "value": null}, {"period": "2022-Q1", "value": null}, {"period": "2022-Q2", "value": null}, {"period": "2022-Q3", "value": null}, {"period": "2023-Q1", "value": null}, {"period": "2023-Q2", "value": null}, {"period": "2023-Q3", "value": 276800000.0}, {"period": "2024-Q1", "value": 256900000.0}, {"period": "2024-Q2", "value": 273800000.0}, {"period": "2024-Q3", "value": 284800000.0}, {"period": "2025-Q1", "value": 281500000.0}, {"period": "2025-Q2", "value": 304100000.0}, {"period": "2025-Q3", "value": 330700000.0}, {"period": "2026-Q1", "value": 325000000.0}]}, {"name": "EMEAMember", "label": "EMEA", "history": [{"period": "2021-Q2", "value": null}, {"period": "2021-Q3", "value": null}, {"period": "2022-Q1", "value": null}, {"period": "2022-Q2", "value": null}, {"period": "2022-Q3", "value": null}, {"period": "2023-Q1", "value": null}, {"period": "2023-Q2", "value": null}, {"period": "2023-Q3", "value": 512200000.0}, {"period": "2024-Q1", "value": 539400000.0}, {"period": "2024-Q2", "value": 565200000.0}, {"period": "2024-Q3", "value": 599300000.0}, {"period": "2025-Q1", "value": 628400000.0}, {"period": "2025-Q2", "value": 667100000.0}, {"period": "2025-Q3", "value": 713700000.0}, {"period": "2026-Q1", "value": 784800000.0}]}, {"name": "EuropeMiddleEastAndAfricaMember", "label": "Europe Middle East And Africa", "history": [{"period": "2021-Q2", "value": 306200000.0}, {"period": "2021-Q3", "value": 323200000.0}, {"period": "2022-Q1", "value": 346000000.0}, {"period": "2022-Q2", "value": 391800000.0}, {"period": "2022-Q3", "value": 443900000.0}, {"period": "2023-Q1", "value": 478200000.0}, {"period": "2023-Q2", "value": 506900000.0}, {"period": "2023-Q3", "value": 512200000.0}, {"period": "2024-Q1", "value": 539400000.0}, {"period": "2024-Q2", "value": 565200000.0}, {"period": "2024-Q3", "value": null}, {"period": "2025-Q1", "value": null}, {"period": "2025-Q2", "value": null}, {"period": "2025-Q3", "value": null}, {"period": "2026-Q1", "value": null}]}, {"name": "OtherAmericasMember", "label": "Other Americas", "history": [{"period": "2021-Q2", "value": 85300000.0}, {"period": "2021-Q3", "value": 91700000.0}, {"period": "2022-Q1", "value": 96800000.0}, {"period": "2022-Q2", "value": 100700000.0}, {"period": "2022-Q3", "value": 123500000.0}, {"period": "2023-Q1", "value": 139400000.0}, {"period": "2023-Q2", "value": 132300000.0}, {"period": "2023-Q3", "value": 144800000.0}, {"period": "2024-Q1", "value": 149900000.0}, {"period": "2024-Q2", "value": 159600000.0}, {"period": "2024-Q3", "value": 168900000.0}, {"period": "2025-Q1", "value": 174400000.0}, {"period": "2025-Q2", "value": 185800000.0}, {"period": "2025-Q3", "value": 193900000.0}, {"period": "2026-Q1", "value": 213300000.0}]}, {"name": "US", "label": "US", "history": [{"period": "2021-Q2", "value": 251700000.0}, {"period": "2021-Q3", "value": 258400000.0}, {"period": "2022-Q1", "value": 285800000.0}, {"period": "2022-Q2", "value": 312900000.0}, {"period": "2022-Q3", "value": 344100000.0}, {"period": "2023-Q1", "value": 384100000.0}, {"period": "2023-Q2", "value": 404700000.0}, {"period": "2023-Q3", "value": 400800000.0}, {"period": "2024-Q1", "value": 407100000.0}, {"period": "2024-Q2", "value": 435700000.0}, {"period": "2024-Q3", "value": 455100000.0}, {"period": "2025-Q1", "value": 455400000.0}, {"period": "2025-Q2", "value": 473000000.0}, {"period": "2025-Q3", "value": 486600000.0}, {"period": "2026-Q1", "value": 526500000.0}]}], "generatedAt": "2026-05-14T16:58:35Z"}
